PyExtender/PErandom.py
PyExtender/__init__.py
PyExtender/bcfo.py
PyExtender/chars.py
PyExtender/otherfunc.py
PyExtender/peError.py
PyExtender/pyassist.py
pyextender-1.1.0a1.dist-info/licenses/LICENSE
pyextender-1.1.0a1.dist-info/METADATA
pyextender-1.1.0a1.dist-info/WHEEL
pyextender-1.1.0a1.dist-info/top_level.txt
pyextender-1.1.0a1.dist-info/RECORD
